seatools/__init__.py
seatools/ext/__init__.py
seatools/ext/chrome/__init__.py
seatools/ext/chrome/chrome.py
seatools/ext/chrome/main.py
seatools/ext/chrome/utils.py
seatools_chrome-1.0.2.dist-info/LICENSE
seatools_chrome-1.0.2.dist-info/METADATA
seatools_chrome-1.0.2.dist-info/WHEEL
seatools_chrome-1.0.2.dist-info/entry_points.txt
seatools_chrome-1.0.2.dist-info/top_level.txt
seatools_chrome-1.0.2.dist-info/RECORD
