Metadata-Version: 2.1
Name: seatools-chrome
Version: 1.0.2
Summary: Cookiecutter-seatools-python chrome拓展工具包
Home-page: https://gitee.com/seatools-py/cookiecutter-seatools-python-chrome
Author: dragons96
Author-email: 521274311@qq.com
License: MIT license
Keywords: seatools,chrome
Classifier: Development Status :: 2 - Pre-Alpha
Classifier: Intended Audience :: Developers
Classifier: License :: OSI Approved :: MIT License
Classifier: Natural Language :: English
Classifier: Programming Language :: Python :: 3.9
Requires-Python: >=3.9
License-File: LICENSE
Requires-Dist: loguru
Requires-Dist: tqdm
Requires-Dist: httpx
Requires-Dist: toml
Requires-Dist: click
